easy_mask/__init__.py
easy_mask/templatetags/easy_mask.py
easy_mask/templatetags/__init__.py
easy_mask/templatetags/utils.py
easy_mask-1.2.3.dist-info/WHEEL
easy_mask-1.2.3.dist-info/METADATA
easy_mask-1.2.3.dist-info/metadata.json
easy_mask-1.2.3.dist-info/RECORD
easy_mask-1.2.3.dist-info/DESCRIPTION.rst
easy_mask-1.2.3.dist-info/top_level.txt
